[
  {"match_number": 1, "date": "2026-03-28", "time_ist": "19:30", "team1": "Royal Challengers Bengaluru", "team2": "Sunrisers Hyderabad", "venue": "M Chinnaswamy Stadium", "city": "Bengaluru", "is_double_header": false},
  {"match_number": 2, "date": "2026-03-29", "time_ist": "19:30", "team1": "Mumbai Indians", "team2": "Kolkata Knight Riders", "venue": "Wankhede Stadium", "city": "Mumbai", "is_double_header": false},
  {"match_number": 3, "date": "2026-03-30", "time_ist": "19:30", "team1": "Rajasthan Royals", "team2": "Chennai Super Kings", "venue": "ACA Cricket Stadium", "city": "Guwahati", "is_double_header": false},
  {"match_number": 4, "date": "2026-03-31", "time_ist": "19:30", "team1": "Punjab Kings", "team2": "Gujarat Titans", "venue": "Maharaja Yadavindra Singh International Cricket Stadium", "city": "Mullanpur", "is_double_header": false},
  {"match_number": 5, "date": "2026-04-01", "time_ist": "19:30", "team1": "Lucknow Super Giants", "team2": "Delhi Capitals", "venue": "BRSABV Ekana Stadium", "city": "Lucknow", "is_double_header": false},
  {"match_number": 6, "date": "2026-04-02", "time_ist": "19:30", "team1": "Kolkata Knight Riders", "team2": "Sunrisers Hyderabad", "venue": "Eden Gardens", "city": "Kolkata", "is_double_header": false},
  {"match_number": 7, "date": "2026-04-03", "time_ist": "19:30", "team1": "Chennai Super Kings", "team2": "Punjab Kings", "venue": "MA Chidambaram Stadium", "city": "Chennai", "is_double_header": false},
  {"match_number": 8, "date": "2026-04-04", "time_ist": "15:30", "team1": "Delhi Capitals", "team2": "Mumbai Indians", "venue": "Arun Jaitley Stadium", "city": "Delhi", "is_double_header": true},
  {"match_number": 9, "date": "2026-04-04", "time_ist": "19:30", "team1": "Gujarat Titans", "team2": "Rajasthan Royals", "venue": "Narendra Modi Stadium", "city": "Ahmedabad", "is_double_header": true},
  {"match_number": 10, "date": "2026-04-05", "time_ist": "15:30", "team1": "Sunrisers Hyderabad", "team2": "Lucknow Super Giants", "venue": "Rajiv Gandhi Intl Stadium", "city": "Hyderabad", "is_double_header": true},
  {"match_number": 11, "date": "2026-04-05", "time_ist": "19:30", "team1": "Royal Challengers Bengaluru", "team2": "Chennai Super Kings", "venue": "M Chinnaswamy Stadium", "city": "Bengaluru", "is_double_header": true},
  {"match_number": 12, "date": "2026-04-06", "time_ist": "19:30", "team1": "Kolkata Knight Riders", "team2": "Punjab Kings", "venue": "Eden Gardens", "city": "Kolkata", "is_double_header": false},
  {"match_number": 13, "date": "2026-04-07", "time_ist": "19:30", "team1": "Rajasthan Royals", "team2": "Mumbai Indians", "venue": "ACA Cricket Stadium", "city": "Guwahati", "is_double_header": false},
  {"match_number": 14, "date": "2026-04-08", "time_ist": "19:30", "team1": "Delhi Capitals", "team2": "Gujarat Titans", "venue": "Arun Jaitley Stadium", "city": "Delhi", "is_double_header": false},
  {"match_number": 15, "date": "2026-04-09", "time_ist": "19:30", "team1": "Kolkata Knight Riders", "team2": "Lucknow Super Giants", "venue": "Eden Gardens", "city": "Kolkata", "is_double_header": false},
  {"match_number": 16, "date": "2026-04-10", "time_ist": "19:30", "team1": "Rajasthan Royals", "team2": "Royal Challengers Bengaluru", "venue": "ACA Cricket Stadium", "city": "Guwahati", "is_double_header": false},
  {"match_number": 17, "date": "2026-04-11", "time_ist": "15:30", "team1": "Punjab Kings", "team2": "Sunrisers Hyderabad", "venue": "Maharaja Yadavindra Singh International Cricket Stadium", "city": "Mullanpur", "is_double_header": true},
  {"match_number": 18, "date": "2026-04-11", "time_ist": "19:30", "team1": "Chennai Super Kings", "team2": "Delhi Capitals", "venue": "MA Chidambaram Stadium", "city": "Chennai", "is_double_header": true},
  {"match_number": 19, "date": "2026-04-12", "time_ist": "15:30", "team1": "Lucknow Super Giants", "team2": "Gujarat Titans", "venue": "BRSABV Ekana Stadium", "city": "Lucknow", "is_double_header": true},
  {"match_number": 20, "date": "2026-04-12", "time_ist": "19:30", "team1": "Mumbai Indians", "team2": "Royal Challengers Bengaluru", "venue": "Wankhede Stadium", "city": "Mumbai", "is_double_header": true},
  {"match_number": 21, "date": "2026-04-13", "time_ist": "19:30", "team1": "Sunrisers Hyderabad", "team2": "Rajasthan Royals", "venue": "Rajiv Gandhi Intl Stadium", "city": "Hyderabad", "is_double_header": false},
  {"match_number": 22, "date": "2026-04-14", "time_ist": "19:30", "team1": "Chennai Super Kings", "team2": "Kolkata Knight Riders", "venue": "MA Chidambaram Stadium", "city": "Chennai", "is_double_header": false},
  {"match_number": 23, "date": "2026-04-15", "time_ist": "19:30", "team1": "Royal Challengers Bengaluru", "team2": "Lucknow Super Giants", "venue": "M Chinnaswamy Stadium", "city": "Bengaluru", "is_double_header": false},
  {"match_number": 24, "date": "2026-04-16", "time_ist": "19:30", "team1": "Mumbai Indians", "team2": "Punjab Kings", "venue": "Wankhede Stadium", "city": "Mumbai", "is_double_header": false},
  {"match_number": 25, "date": "2026-04-17", "time_ist": "19:30", "team1": "Gujarat Titans", "team2": "Kolkata Knight Riders", "venue": "Narendra Modi Stadium", "city": "Ahmedabad", "is_double_header": false},
  {"match_number": 26, "date": "2026-04-18", "time_ist": "15:30", "team1": "Royal Challengers Bengaluru", "team2": "Delhi Capitals", "venue": "M Chinnaswamy Stadium", "city": "Bengaluru", "is_double_header": true},
  {"match_number": 27, "date": "2026-04-18", "time_ist": "19:30", "team1": "Sunrisers Hyderabad", "team2": "Chennai Super Kings", "venue": "Rajiv Gandhi Intl Stadium", "city": "Hyderabad", "is_double_header": true},
  {"match_number": 28, "date": "2026-04-19", "time_ist": "15:30", "team1": "Kolkata Knight Riders", "team2": "Rajasthan Royals", "venue": "Eden Gardens", "city": "Kolkata", "is_double_header": true},
  {"match_number": 29, "date": "2026-04-19", "time_ist": "19:30", "team1": "Punjab Kings", "team2": "Lucknow Super Giants", "venue": "Maharaja Yadavindra Singh International Cricket Stadium", "city": "Mullanpur", "is_double_header": true},
  {"match_number": 30, "date": "2026-04-20", "time_ist": "19:30", "team1": "Gujarat Titans", "team2": "Mumbai Indians", "venue": "Narendra Modi Stadium", "city": "Ahmedabad", "is_double_header": false},
  {"match_number": 31, "date": "2026-04-21", "time_ist": "19:30", "team1": "Sunrisers Hyderabad", "team2": "Delhi Capitals", "venue": "Rajiv Gandhi Intl Stadium", "city": "Hyderabad", "is_double_header": false},
  {"match_number": 32, "date": "2026-04-22", "time_ist": "19:30", "team1": "Lucknow Super Giants", "team2": "Rajasthan Royals", "venue": "BRSABV Ekana Stadium", "city": "Lucknow", "is_double_header": false},
  {"match_number": 33, "date": "2026-04-23", "time_ist": "19:30", "team1": "Mumbai Indians", "team2": "Chennai Super Kings", "venue": "Wankhede Stadium", "city": "Mumbai", "is_double_header": false},
  {"match_number": 34, "date": "2026-04-24", "time_ist": "19:30", "team1": "Royal Challengers Bengaluru", "team2": "Gujarat Titans", "venue": "M Chinnaswamy Stadium", "city": "Bengaluru", "is_double_header": false},
  {"match_number": 35, "date": "2026-04-25", "time_ist": "15:30", "team1": "Delhi Capitals", "team2": "Punjab Kings", "venue": "Arun Jaitley Stadium", "city": "Delhi", "is_double_header": true},
  {"match_number": 36, "date": "2026-04-25", "time_ist": "19:30", "team1": "Rajasthan Royals", "team2": "Sunrisers Hyderabad", "venue": "Sawai Mansingh Stadium", "city": "Jaipur", "is_double_header": true},
  {"match_number": 37, "date": "2026-04-26", "time_ist": "15:30", "team1": "Gujarat Titans", "team2": "Chennai Super Kings", "venue": "Narendra Modi Stadium", "city": "Ahmedabad", "is_double_header": true},
  {"match_number": 38, "date": "2026-04-26", "time_ist": "19:30", "team1": "Lucknow Super Giants", "team2": "Kolkata Knight Riders", "venue": "BRSABV Ekana Stadium", "city": "Lucknow", "is_double_header": true},
  {"match_number": 39, "date": "2026-04-27", "time_ist": "19:30", "team1": "Delhi Capitals", "team2": "Royal Challengers Bengaluru", "venue": "Arun Jaitley Stadium", "city": "Delhi", "is_double_header": false},
  {"match_number": 40, "date": "2026-04-28", "time_ist": "19:30", "team1": "Punjab Kings", "team2": "Rajasthan Royals", "venue": "Maharaja Yadavindra Singh International Cricket Stadium", "city": "Mullanpur", "is_double_header": false},
  {"match_number": 41, "date": "2026-04-29", "time_ist": "19:30", "team1": "Mumbai Indians", "team2": "Sunrisers Hyderabad", "venue": "Wankhede Stadium", "city": "Mumbai", "is_double_header": false},
  {"match_number": 42, "date": "2026-04-30", "time_ist": "19:30", "team1": "Gujarat Titans", "team2": "Royal Challengers Bengaluru", "venue": "Narendra Modi Stadium", "city": "Ahmedabad", "is_double_header": false},
  {"match_number": 43, "date": "2026-05-01", "time_ist": "19:30", "team1": "Rajasthan Royals", "team2": "Delhi Capitals", "venue": "Sawai Mansingh Stadium", "city": "Jaipur", "is_double_header": false},
  {"match_number": 44, "date": "2026-05-02", "time_ist": "19:30", "team1": "Chennai Super Kings", "team2": "Mumbai Indians", "venue": "MA Chidambaram Stadium", "city": "Chennai", "is_double_header": false},
  {"match_number": 45, "date": "2026-05-03", "time_ist": "15:30", "team1": "Sunrisers Hyderabad", "team2": "Kolkata Knight Riders", "venue": "Rajiv Gandhi Intl Stadium", "city": "Hyderabad", "is_double_header": true},
  {"match_number": 46, "date": "2026-05-03", "time_ist": "19:30", "team1": "Gujarat Titans", "team2": "Punjab Kings", "venue": "Narendra Modi Stadium", "city": "Ahmedabad", "is_double_header": true},
  {"match_number": 47, "date": "2026-05-04", "time_ist": "19:30", "team1": "Mumbai Indians", "team2": "Lucknow Super Giants", "venue": "Wankhede Stadium", "city": "Mumbai", "is_double_header": false},
  {"match_number": 48, "date": "2026-05-05", "time_ist": "19:30", "team1": "Delhi Capitals", "team2": "Chennai Super Kings", "venue": "Arun Jaitley Stadium", "city": "Delhi", "is_double_header": false},
  {"match_number": 49, "date": "2026-05-06", "time_ist": "15:30", "team1": "Sunrisers Hyderabad", "team2": "Punjab Kings", "venue": "Rajiv Gandhi Intl Stadium", "city": "Hyderabad", "is_double_header": false},
  {"match_number": 50, "date": "2026-05-07", "time_ist": "19:30", "team1": "Lucknow Super Giants", "team2": "Royal Challengers Bengaluru", "venue": "BRSABV Ekana Stadium", "city": "Lucknow", "is_double_header": false},
  {"match_number": 51, "date": "2026-05-08", "time_ist": "19:30", "team1": "Delhi Capitals", "team2": "Kolkata Knight Riders", "venue": "Arun Jaitley Stadium", "city": "Delhi", "is_double_header": false},
  {"match_number": 52, "date": "2026-05-09", "time_ist": "19:30", "team1": "Rajasthan Royals", "team2": "Gujarat Titans", "venue": "Sawai Mansingh Stadium", "city": "Jaipur", "is_double_header": false},
  {"match_number": 53, "date": "2026-05-10", "time_ist": "15:30", "team1": "Chennai Super Kings", "team2": "Lucknow Super Giants", "venue": "MA Chidambaram Stadium", "city": "Chennai", "is_double_header": true},
  {"match_number": 54, "date": "2026-05-10", "time_ist": "19:30", "team1": "Royal Challengers Bengaluru", "team2": "Mumbai Indians", "venue": "Nava Raipur Cricket Stadium", "city": "Raipur", "is_double_header": true},
  {"match_number": 55, "date": "2026-05-11", "time_ist": "19:30", "team1": "Punjab Kings", "team2": "Delhi Capitals", "venue": "HPCA Cricket Stadium", "city": "Dharamsala", "is_double_header": false},
  {"match_number": 56, "date": "2026-05-12", "time_ist": "19:30", "team1": "Gujarat Titans", "team2": "Sunrisers Hyderabad", "venue": "Narendra Modi Stadium", "city": "Ahmedabad", "is_double_header": false},
  {"match_number": 57, "date": "2026-05-13", "time_ist": "19:30", "team1": "Royal Challengers Bengaluru", "team2": "Kolkata Knight Riders", "venue": "Nava Raipur Cricket Stadium", "city": "Raipur", "is_double_header": false},
  {"match_number": 58, "date": "2026-05-14", "time_ist": "19:30", "team1": "Punjab Kings", "team2": "Mumbai Indians", "venue": "HPCA Cricket Stadium", "city": "Dharamsala", "is_double_header": false},
  {"match_number": 59, "date": "2026-05-15", "time_ist": "19:30", "team1": "Lucknow Super Giants", "team2": "Chennai Super Kings", "venue": "BRSABV Ekana Stadium", "city": "Lucknow", "is_double_header": false},
  {"match_number": 60, "date": "2026-05-16", "time_ist": "19:30", "team1": "Kolkata Knight Riders", "team2": "Gujarat Titans", "venue": "Eden Gardens", "city": "Kolkata", "is_double_header": false},
  {"match_number": 61, "date": "2026-05-17", "time_ist": "15:30", "team1": "Punjab Kings", "team2": "Royal Challengers Bengaluru", "venue": "HPCA Cricket Stadium", "city": "Dharamsala", "is_double_header": true},
  {"match_number": 62, "date": "2026-05-17", "time_ist": "19:30", "team1": "Delhi Capitals", "team2": "Rajasthan Royals", "venue": "Arun Jaitley Stadium", "city": "Delhi", "is_double_header": true},
  {"match_number": 63, "date": "2026-05-18", "time_ist": "19:30", "team1": "Chennai Super Kings", "team2": "Sunrisers Hyderabad", "venue": "MA Chidambaram Stadium", "city": "Chennai", "is_double_header": false},
  {"match_number": 64, "date": "2026-05-19", "time_ist": "19:30", "team1": "Rajasthan Royals", "team2": "Lucknow Super Giants", "venue": "Sawai Mansingh Stadium", "city": "Jaipur", "is_double_header": false},
  {"match_number": 65, "date": "2026-05-20", "time_ist": "19:30", "team1": "Kolkata Knight Riders", "team2": "Mumbai Indians", "venue": "Eden Gardens", "city": "Kolkata", "is_double_header": false},
  {"match_number": 66, "date": "2026-05-21", "time_ist": "19:30", "team1": "Chennai Super Kings", "team2": "Gujarat Titans", "venue": "MA Chidambaram Stadium", "city": "Chennai", "is_double_header": false},
  {"match_number": 67, "date": "2026-05-22", "time_ist": "15:30", "team1": "Sunrisers Hyderabad", "team2": "Royal Challengers Bengaluru", "venue": "Rajiv Gandhi Intl Stadium", "city": "Hyderabad", "is_double_header": false},
  {"match_number": 68, "date": "2026-05-23", "time_ist": "19:30", "team1": "Lucknow Super Giants", "team2": "Punjab Kings", "venue": "BRSABV Ekana Stadium", "city": "Lucknow", "is_double_header": false},
  {"match_number": 69, "date": "2026-05-24", "time_ist": "15:30", "team1": "Mumbai Indians", "team2": "Rajasthan Royals", "venue": "Wankhede Stadium", "city": "Mumbai", "is_double_header": true},
  {"match_number": 70, "date": "2026-05-24", "time_ist": "19:30", "team1": "Kolkata Knight Riders", "team2": "Delhi Capitals", "venue": "Eden Gardens", "city": "Kolkata", "is_double_header": true},
  {"match_number": 71, "date": "2026-05-26", "time_ist": "19:30", "team1": "Qualifier 1", "team2": "TBD", "venue": "TBD", "city": "TBD", "is_double_header": false, "stage": "playoff"},
  {"match_number": 72, "date": "2026-05-27", "time_ist": "19:30", "team1": "Eliminator", "team2": "TBD", "venue": "TBD", "city": "TBD", "is_double_header": false, "stage": "playoff"},
  {"match_number": 73, "date": "2026-05-29", "time_ist": "19:30", "team1": "Qualifier 2", "team2": "TBD", "venue": "TBD", "city": "TBD", "is_double_header": false, "stage": "playoff"},
  {"match_number": 74, "date": "2026-05-31", "time_ist": "19:30", "team1": "Final", "team2": "TBD", "venue": "M Chinnaswamy Stadium", "city": "Bengaluru", "is_double_header": false, "stage": "final"}
]
